example_package/__init__.py
example_package/example.py
fastagent-0.0.1.dist-info/LICENSE
fastagent-0.0.1.dist-info/METADATA
fastagent-0.0.1.dist-info/WHEEL
fastagent-0.0.1.dist-info/top_level.txt
fastagent-0.0.1.dist-info/RECORD
