Metadata-Version: 2.1
Name: fastagent
Version: 0.0.1
Summary: Build AI agent fast.
Home-page: https://github.com/maxloge/fastagent
Author: Maxime Logé
Author-email: max.loge@gmail.com
License: UNKNOWN
Project-URL: Bug Tracker, https://github.com/maxloge/fastagent/issues
Platform: UNKNOWN
Classifier: Programming Language :: Python :: 3
Classifier: License :: OSI Approved :: Apache Software License
Classifier: Operating System :: OS Independent
Requires-Python: >=3.6
License-File: LICENSE
